[
    {
      "pooja": "Oru Divasa Pooja",
      "price": "9000.00"
    },
    {
      "pooja": "Ekadasa Rudrabishekam",
      "price": "7000.00"
    },
    {
      "pooja": "Viseshal Navagraha Pooja",
      "price": "4500.00"
    },
    {
      "pooja": "Ekagraha Santhi",
      "price": "2000.00"
    },
    {
      "pooja": "Maha Mrithwinjaya Homam",
      "price": "7500.00"
    },
    {
      "pooja": "Pradosham",
      "price": "450.00"
    },
    {
      "pooja": "Udayasthamanapooja",
      "price": "1000.00"
    },
    {
      "pooja": "Uma Maheswara Pooja",
      "price": "50.00"
    },
    {
      "pooja": "Bhrahmarakshas Pooja",
      "price": "50.00"
    },
    {
      "pooja": "Panchamritham",
      "price": "60.00"
    },
    {
      "pooja": "Ganapathy Homam",
      "price": "80.00"
    },
    {
      "pooja": "Mrithwinjaya Homam",
      "price": "60.00"
    },
    {
      "pooja": "Karuka Homam",
      "price": "60.00"
    },
    {
      "pooja": "Ayuss Homam",
      "price": "60.00"
    },
    {
      "pooja": "Neyvilakku",
      "price": "10.00"
    },
    {
      "pooja": "Ashtothararchana",
      "price": "10.00"
    },
    {
      "pooja": "Swayamvararchana",
      "price": "40.00"
    },
    {
      "pooja": "Kunkumarchana",
      "price": "10.00"
    },
    {
      "pooja": "Sahasranama Kunkumarchana",
      "price": "150.00"
    },
    {
      "pooja": "Siva Sahasranamarchana",
      "price": "50.00"
    },
    {
      "pooja": "Pradosha radha Prayanam",
      "price": "2000.00"
    },
    {
      "pooja": "Mrithwinjayarchana",
      "price": "20.00"
    },
    {
      "pooja": "Dambathi Archana",
      "price": "50.00"
    },
    {
      "pooja": "Rudrabhishekam",
      "price": "400.00"
    },
    {
      "pooja": "Palabishekam",
      "price": "10.00"
    },
    {
      "pooja": "Manjal Abhishekam",
      "price": "50.00"
    },
    {
      "pooja": "Dhara",
      "price": "50.00"
    },
    {
      "pooja": "Jala Dhara",
      "price": "10.00"
    },
    {
      "pooja": "Ney Payasam",
      "price": "100.00"
    },
    {
      "pooja": "Palppayasam",
      "price": "80.00"
    },
    {
      "pooja": "Sabarimala Malayidal",
      "price": "10.00"
    },
    {
      "pooja": "Kettunira",
      "price": "10.00"
    },
    {
      "pooja": "Vazhipadu sadhanangal Charthal",
      "price": "10.00"
    },
    {
      "pooja": "Vivaham",
      "price": "250.00"
    },
    {
      "pooja": "Choroon",
      "price": "50.00"
    },
    {
      "pooja": "Chuttuvilakku",
      "price": "1100.00"
    },
    {
      "pooja": "Naga Pooja",
      "price": "100.00"
    },
    {
      "pooja": "Pithrudharppanam",
      "price": "30.00"
    },
    {
      "pooja": "Thulabharam",
      "price": "300.00"
    }
  ]